crepex_django_util/__init__.py
crepex_django_util/admin/__init__.py
crepex_django_util/admin/actions.py
crepex_django_util/admin/utils.py
crepex_django_util/exceptions.py
crepex_django_util/fields.py
crepex_django_util/filters.py
crepex_django_util/models/__init__.py
crepex_django_util/models/inheritance.py
crepex_django_util/paginations.py
crepex_django_util/payments/__init__.py
crepex_django_util/payments/payple.py
crepex_django_util/payments/types.py
crepex_django_util/permissions.py
crepex_django_util/serializers/__init__.py
crepex_django_util/serializers/generics.py
crepex_django_util/serializers/mixins.py
crepex_django_util/settings.py
crepex_django_util/utils.py
crepex_django_util/validators.py
crepex_django_util/views/__init__.py
crepex_django_util/views/generics.py
crepex_django_util/views/mixins.py
crepex_django_util-0.7.4.dist-info/METADATA
crepex_django_util-0.7.4.dist-info/WHEEL
crepex_django_util-0.7.4.dist-info/RECORD
