Metadata-Version: 2.1
Name: crepex-django-util
Version: 0.7.4
Summary: CrepeX django utilities
Author: Hyunwoo Shim
Author-email: hyunwoo.shim@crepe-x.com
Requires-Python: >=3.8,<4.0
Classifier: Programming Language :: Python :: 3
Classifier: Programming Language :: Python :: 3.8
Classifier: Programming Language :: Python :: 3.9
Classifier: Programming Language :: Python :: 3.10
Classifier: Programming Language :: Python :: 3.11
Classifier: Programming Language :: Python :: 3.12
Requires-Dist: crepex-pyutil (>=0.14.0,<1.0.0)
